tests/__init__.py
tests/test_elasticsearch.py
tests/test_import.py
workshop/__init__.py
workshop/elasticsearch/__init__.py
workshop/elasticsearch/api.py
workshop/elasticsearch/session.py
vunk_workshop-0.0.2.dist-info/LICENSE
vunk_workshop-0.0.2.dist-info/METADATA
vunk_workshop-0.0.2.dist-info/WHEEL
vunk_workshop-0.0.2.dist-info/top_level.txt
vunk_workshop-0.0.2.dist-info/RECORD
