Metadata-Version: 2.1
Name: vunk-workshop
Version: 0.0.2
Summary: My toolkits
Home-page: https://github.com/VunkLai/vunk
Author: Vunk.Lai
Author-email: vunk.lai@gmail.com
License: MIT
Platform: UNKNOWN
Classifier: Programming Language :: Python :: 3
Classifier: License :: OSI Approved :: MIT License
Classifier: Operating System :: OS Independent
Requires-Python: >=3.7
